ngramtg/__init__.py
ngramtg/exceptions.py
ngramtg/ngram.py
tests/__init__.py
tests/test_ngramtg.py
ngramtg-2019.1.dist-info/LICENSE
ngramtg-2019.1.dist-info/METADATA
ngramtg-2019.1.dist-info/WHEEL
ngramtg-2019.1.dist-info/top_level.txt
ngramtg-2019.1.dist-info/RECORD
