Metadata-Version: 2.1
Name: ngramtg
Version: 2019.1
Summary: A simple ngram-based random text generator.
Home-page: https://github.com/docwicking/ngramtg
Author: Paul Wicking
Author-email: paulwicking@gmail.com
License: UNKNOWN
Platform: UNKNOWN
Classifier: Programming Language :: Python :: 3
Classifier: License :: OSI Approved :: MIT License
Classifier: Operating System :: OS Independent
